pyargdown/__about__.py
pyargdown/__init__.py
pyargdown-0.0.1.dist-info/METADATA
pyargdown-0.0.1.dist-info/WHEEL
pyargdown-0.0.1.dist-info/licenses/LICENSE
pyargdown-0.0.1.dist-info/RECORD
